{"diagnostic": true, "poly_condition_id": "0x0ed2e5e985631ab71750ad21a40503508a5f7d928032b2d1f8c901013f4e002f", "kalshi_ticker": "KXWCCONTINENT-26-SA", "note": "南美(CONMEBOL)夺冠（待人工确认）", "combo": "poly_yes+kalshi_no", "poly_price": 0.2, "kalshi_price": 0.81, "kalshi_fee": 0.010773, "sum_cost": 1.020773, "edge_per_pair": -0.020773, "depth": 912.48, "poly_question": "Will South America (CONMEBOL) win the 2026 FIFA World Cup?"}
{"diagnostic": true, "poly_condition_id": "0x3561a95d16ac2edfd3831aba4612c88c6f5b84a6f0924bdb6b07dc7cfe73e121", "kalshi_ticker": "KXWCCONTINENT-26-EUR", "note": "欧洲(UEFA)夺冠（待人工确认）", "combo": "poly_yes+kalshi_no", "poly_price": 0.8, "kalshi_price": 0.2, "kalshi_fee": 0.0112, "sum_cost": 1.0112, "edge_per_pair": -0.0112, "depth": 502.0, "poly_question": "Will Europe (UEFA) win the 2026 FIFA World Cup?"}
